[
 {
  "date": "Tue, 16 Jul 2013 10:58:33 GMT", 
  "link": "http://www.cnbeta.com/articles/244894.htm", 
  "description": "<p><strong>Firefox 23.0的进展相当迅速，Beta 6已经来到Beta测试目录中，</strong>新版开始采用Gecko 23内核，预计正式发布时间2013年8月，Moziila在新版本23中加入了混合内容锁定模式，保证了在安全传输模式下第三方中间人攻击无法实施，此外开始对OS X 10.7以上版本提供了新的滑动导航动画等新特性。</p><img border=\"0\" height=\"1\" src=\"http://cnbeta.feedsportal.com/c/34306/f/624776/s/2eb9b1cf/mf.gif\" width=\"1\" /><div class=\"mf-viral\"><table border=\"0\"><tr><td valign=\"middle\"><a href=\"http://share.feedsportal.com/share/twitter/?u=http%3A%2F%2Fwww.cnbeta.com%2Farticles%2F244894.htm&amp;t=Mozilla+Firefox+23.0+Beta+6+%E5%8F%91%E5%B8%83\" target=\"_blank\"><img border=\"0\" src=\"http://res3.feedsportal.com/social/twitter.png\" /></a>&nbsp;<a href=\"http://share.feedsportal.com/share/facebook/?u=http%3A%2F%2Fwww.cnbeta.com%2Farticles%2F244894.htm&amp;t=Mozilla+Firefox+23.0+Beta+6+%E5%8F%91%E5%B8%83\" target=\"_blank\"><img border=\"0\" src=\"http://res3.feedsportal.com/social/facebook.png\" /></a>&nbsp;<a href=\"http://share.feedsportal.com/share/linkedin/?u=http%3A%2F%2Fwww.cnbeta.com%2Farticles%2F244894.htm&amp;t=Mozilla+Firefox+23.0+Beta+6+%E5%8F%91%E5%B8%83\" target=\"_blank\"><img border=\"0\" src=\"http://res3.feedsportal.com/social/linkedin.png\" /></a>&nbsp;<a href=\"http://share.feedsportal.com/share/gplus/?u=http%3A%2F%2Fwww.cnbeta.com%2Farticles%2F244894.htm&amp;t=Mozilla+Firefox+23.0+Beta+6+%E5%8F%91%E5%B8%83\" target=\"_blank\"><img border=\"0\" src=\"http://res3.feedsportal.com/social/googleplus.png\" /></a>&nbsp;<a href=\"http://share.feedsportal.com/share/email/?u=http%3A%2F%2Fwww.cnbeta.com%2Farticles%2F244894.htm&amp;t=Mozilla+Firefox+23.0+Beta+6+%E5%8F%91%E5%B8%83\" target=\"_blank\"><img border=\"0\" src=\"http://res3.feedsportal.com/social/email.png\" /></a></td><td valign=\"middle\"></td></tr></table></div><br /><br /><a href=\"http://da.feedsportal.com/r/165666653724/u/0/f/624776/c/34306/s/2eb9b1cf/a2.htm\"><img border=\"0\" src=\"http://da.feedsportal.com/r/165666653724/u/0/f/624776/c/34306/s/2eb9b1cf/a2.img\" /></a><img border=\"0\" height=\"1\" src=\"http://pi.feedsportal.com/r/165666653724/u/0/f/624776/c/34306/s/2eb9b1cf/a2t.img\" width=\"1\" />", 
  "title": "Mozilla Firefox 23.0 Beta 6 发布"
 }, 
 {
  "date": "Tue, 16 Jul 2013 10:54:15 GMT", 
  "link": "http://www.cnbeta.com/articles/244893.htm", 
  "description": "<p>长途旅行途中总是很无聊，在飞机上用上互联网，这个无数乘客梦寐以求的愿望终于实现。<strong>7月3日，从北京飞往成都的国航CA4108航班上，乘客们终 于在万米高空体验了一把无线上网，可以接入互联网发微博、查股票。这架飞机采用的就是空地互联技术实现的互联网接入，下面就来为大家详细介绍这个技术。</strong></p><img border=\"0\" height=\"1\" src=\"http://cnbeta.feedsportal.com/c/34306/f/624776/s/2eb9b1cd/mf.gif\" width=\"1\" /><div class=\"mf-viral\"><table border=\"0\"><tr><td valign=\"middle\"><a href=\"http://share.feedsportal.com/share/twitter/?u=http%3A%2F%2Fwww.cnbeta.com%2Farticles%2F244893.htm&amp;t=%E9%A3%9E%E6%9C%BA%E7%A9%BA%E5%9C%B0%E4%BA%92%E8%81%94%E8%A7%A3%E6%9E%90%3A%E4%B8%87%E7%B1%B3%E9%AB%98%E7%A9%BA%E5%A6%82%E4%BD%95%E7%94%A8%E4%B8%8A%E4%BA%92%E8%81%94%E7%BD%91%E6%8E%A5%E5%85%A5\" target=\"_blank\"><img border=\"0\" src=\"http://res3.feedsportal.com/social/twitter.png\" /></a>&nbsp;<a href=\"http://share.feedsportal.com/share/facebook/?u=http%3A%2F%2Fwww.cnbeta.com%2Farticles%2F244893.htm&amp;t=%E9%A3%9E%E6%9C%BA%E7%A9%BA%E5%9C%B0%E4%BA%92%E8%81%94%E8%A7%A3%E6%9E%90%3A%E4%B8%87%E7%B1%B3%E9%AB%98%E7%A9%BA%E5%A6%82%E4%BD%95%E7%94%A8%E4%B8%8A%E4%BA%92%E8%81%94%E7%BD%91%E6%8E%A5%E5%85%A5\" target=\"_blank\"><img border=\"0\" src=\"http://res3.feedsportal.com/social/facebook.png\" /></a>&nbsp;<a href=\"http://share.feedsportal.com/share/linkedin/?u=http%3A%2F%2Fwww.cnbeta.com%2Farticles%2F244893.htm&amp;t=%E9%A3%9E%E6%9C%BA%E7%A9%BA%E5%9C%B0%E4%BA%92%E8%81%94%E8%A7%A3%E6%9E%90%3A%E4%B8%87%E7%B1%B3%E9%AB%98%E7%A9%BA%E5%A6%82%E4%BD%95%E7%94%A8%E4%B8%8A%E4%BA%92%E8%81%94%E7%BD%91%E6%8E%A5%E5%85%A5\" target=\"_blank\"><img border=\"0\" src=\"http://res3.feedsportal.com/social/linkedin.png\" /></a>&nbsp;<a href=\"http://share.feedsportal.com/share/gplus/?u=http%3A%2F%2Fwww.cnbeta.com%2Farticles%2F244893.htm&amp;t=%E9%A3%9E%E6%9C%BA%E7%A9%BA%E5%9C%B0%E4%BA%92%E8%81%94%E8%A7%A3%E6%9E%90%3A%E4%B8%87%E7%B1%B3%E9%AB%98%E7%A9%BA%E5%A6%82%E4%BD%95%E7%94%A8%E4%B8%8A%E4%BA%92%E8%81%94%E7%BD%91%E6%8E%A5%E5%85%A5\" target=\"_blank\"><img border=\"0\" src=\"http://res3.feedsportal.com/social/googleplus.png\" /></a>&nbsp;<a href=\"http://share.feedsportal.com/share/email/?u=http%3A%2F%2Fwww.cnbeta.com%2Farticles%2F244893.htm&amp;t=%E9%A3%9E%E6%9C%BA%E7%A9%BA%E5%9C%B0%E4%BA%92%E8%81%94%E8%A7%A3%E6%9E%90%3A%E4%B8%87%E7%B1%B3%E9%AB%98%E7%A9%BA%E5%A6%82%E4%BD%95%E7%94%A8%E4%B8%8A%E4%BA%92%E8%81%94%E7%BD%91%E6%8E%A5%E5%85%A5\" target=\"_blank\"><img border=\"0\" src=\"http://res3.feedsportal.com/social/email.png\" /></a></td><td valign=\"middle\"></td></tr></table></div><br /><br /><a href=\"http://da.feedsportal.com/r/165666653723/u/0/f/624776/c/34306/s/2eb9b1cd/a2.htm\"><img border=\"0\" src=\"http://da.feedsportal.com/r/165666653723/u/0/f/624776/c/34306/s/2eb9b1cd/a2.img\" /></a><img border=\"0\" height=\"1\" src=\"http://pi.feedsportal.com/r/165666653723/u/0/f/624776/c/34306/s/2eb9b1cd/a2t.img\" width=\"1\" />", 
  "title": "飞机空地互联解析:万米高空如何用上互联网接入"
 }, 
 {
  "date": "Tue, 16 Jul 2013 10:53:32 GMT", 
  "link": "http://www.cnbeta.com/articles/244892.htm", 
  "description": "<p><strong>“8位人工，平均每天在天猫直通车烧钱3000元。各种价格大战、打折促销、存货若干、亏损一年。继续做，继续亏；不做，亏的打水漂。你觉得我该怎么继续做？”</strong>7月9日，一位持续关注本报“天猫造假系列报道”的天猫某女装专营店店主张桦(化名)对黄枪大倒苦水。</p><img border=\"0\" height=\"1\" src=\"http://cnbeta.feedsportal.com/c/34306/f/624776/s/2eb9b1cb/mf.gif\" width=\"1\" /><div class=\"mf-viral\"><table border=\"0\"><tr><td valign=\"middle\"><a href=\"http://share.feedsportal.com/share/twitter/?u=http%3A%2F%2Fwww.cnbeta.com%2Farticles%2F244892.htm&amp;t=%E8%B4%AA%E5%A9%AA%E5%A4%A9%E7%8C%AB%E5%81%87%E8%B4%A7%E6%B3%9B%E6%BB%A5%EF%BC%9A%E8%A7%84%E5%88%99%E6%BC%8F%E6%B4%9E%E7%99%BE%E5%87%BA\" target=\"_blank\"><img border=\"0\" src=\"http://res3.feedsportal.com/social/twitter.png\" /></a>&nbsp;<a href=\"http://share.feedsportal.com/share/facebook/?u=http%3A%2F%2Fwww.cnbeta.com%2Farticles%2F244892.htm&amp;t=%E8%B4%AA%E5%A9%AA%E5%A4%A9%E7%8C%AB%E5%81%87%E8%B4%A7%E6%B3%9B%E6%BB%A5%EF%BC%9A%E8%A7%84%E5%88%99%E6%BC%8F%E6%B4%9E%E7%99%BE%E5%87%BA\" target=\"_blank\"><img border=\"0\" src=\"http://res3.feedsportal.com/social/facebook.png\" /></a>&nbsp;<a href=\"http://share.feedsportal.com/share/linkedin/?u=http%3A%2F%2Fwww.cnbeta.com%2Farticles%2F244892.htm&amp;t=%E8%B4%AA%E5%A9%AA%E5%A4%A9%E7%8C%AB%E5%81%87%E8%B4%A7%E6%B3%9B%E6%BB%A5%EF%BC%9A%E8%A7%84%E5%88%99%E6%BC%8F%E6%B4%9E%E7%99%BE%E5%87%BA\" target=\"_blank\"><img border=\"0\" src=\"http://res3.feedsportal.com/social/linkedin.png\" /></a>&nbsp;<a href=\"http://share.feedsportal.com/share/gplus/?u=http%3A%2F%2Fwww.cnbeta.com%2Farticles%2F244892.htm&amp;t=%E8%B4%AA%E5%A9%AA%E5%A4%A9%E7%8C%AB%E5%81%87%E8%B4%A7%E6%B3%9B%E6%BB%A5%EF%BC%9A%E8%A7%84%E5%88%99%E6%BC%8F%E6%B4%9E%E7%99%BE%E5%87%BA\" target=\"_blank\"><img border=\"0\" src=\"http://res3.feedsportal.com/social/googleplus.png\" /></a>&nbsp;<a href=\"http://share.feedsportal.com/share/email/?u=http%3A%2F%2Fwww.cnbeta.com%2Farticles%2F244892.htm&amp;t=%E8%B4%AA%E5%A9%AA%E5%A4%A9%E7%8C%AB%E5%81%87%E8%B4%A7%E6%B3%9B%E6%BB%A5%EF%BC%9A%E8%A7%84%E5%88%99%E6%BC%8F%E6%B4%9E%E7%99%BE%E5%87%BA\" target=\"_blank\"><img border=\"0\" src=\"http://res3.feedsportal.com/social/email.png\" /></a></td><td valign=\"middle\"></td></tr></table></div><br /><br /><a href=\"http://da.feedsportal.com/r/165666653721/u/0/f/624776/c/34306/s/2eb9b1cb/a2.htm\"><img border=\"0\" src=\"http://da.feedsportal.com/r/165666653721/u/0/f/624776/c/34306/s/2eb9b1cb/a2.img\" /></a><img border=\"0\" height=\"1\" src=\"http://pi.feedsportal.com/r/165666653721/u/0/f/624776/c/34306/s/2eb9b1cb/a2t.img\" width=\"1\" />", 
  "title": "贪婪天猫假货泛滥：规则漏洞百出"
 }, 
 {
  "date": "Tue, 16 Jul 2013 10:52:14 GMT", 
  "link": "http://www.cnbeta.com/articles/244891.htm", 
  "description": "<p>硅谷市场研究公司Creative Strategies总裁蒂姆·巴加林(Tim Bajarin)今日在《时代》杂志网络版上撰文指出，<strong>微软在设计Windows 8时，逻辑上存在缺陷，没有采用循序渐进的策略，让用户有一个自然的适应过程，反而强行要求PC厂商增加触控屏，这不仅大大增加了产品成本，也让本就承受 平板电脑重压的PC市场，进一步滑向衰退的深渊。以下为文章全文：</strong></p><img border=\"0\" height=\"1\" src=\"http://cnbeta.feedsportal.com/c/34306/f/624776/s/2eb9b1c9/mf.gif\" width=\"1\" /><div class=\"mf-viral\"><table border=\"0\"><tr><td valign=\"middle\"><a href=\"http://share.feedsportal.com/share/twitter/?u=http%3A%2F%2Fwww.cnbeta.com%2Farticles%2F244891.htm&amp;t=%E3%80%8A%E6%97%B6%E4%BB%A3%E3%80%8B%E6%9D%82%E5%BF%97%EF%BC%9A%E5%BE%AE%E8%BD%AFWindows+8%E8%AE%BE%E8%AE%A1%E9%80%BB%E8%BE%91%E5%AD%98%E5%9C%A8%E7%BC%BA%E9%99%B7\" target=\"_blank\"><img border=\"0\" src=\"http://res3.feedsportal.com/social/twitter.png\" /></a>&nbsp;<a href=\"http://share.feedsportal.com/share/facebook/?u=http%3A%2F%2Fwww.cnbeta.com%2Farticles%2F244891.htm&amp;t=%E3%80%8A%E6%97%B6%E4%BB%A3%E3%80%8B%E6%9D%82%E5%BF%97%EF%BC%9A%E5%BE%AE%E8%BD%AFWindows+8%E8%AE%BE%E8%AE%A1%E9%80%BB%E8%BE%91%E5%AD%98%E5%9C%A8%E7%BC%BA%E9%99%B7\" target=\"_blank\"><img border=\"0\" src=\"http://res3.feedsportal.com/social/facebook.png\" /></a>&nbsp;<a href=\"http://share.feedsportal.com/share/linkedin/?u=http%3A%2F%2Fwww.cnbeta.com%2Farticles%2F244891.htm&amp;t=%E3%80%8A%E6%97%B6%E4%BB%A3%E3%80%8B%E6%9D%82%E5%BF%97%EF%BC%9A%E5%BE%AE%E8%BD%AFWindows+8%E8%AE%BE%E8%AE%A1%E9%80%BB%E8%BE%91%E5%AD%98%E5%9C%A8%E7%BC%BA%E9%99%B7\" target=\"_blank\"><img border=\"0\" src=\"http://res3.feedsportal.com/social/linkedin.png\" /></a>&nbsp;<a href=\"http://share.feedsportal.com/share/gplus/?u=http%3A%2F%2Fwww.cnbeta.com%2Farticles%2F244891.htm&amp;t=%E3%80%8A%E6%97%B6%E4%BB%A3%E3%80%8B%E6%9D%82%E5%BF%97%EF%BC%9A%E5%BE%AE%E8%BD%AFWindows+8%E8%AE%BE%E8%AE%A1%E9%80%BB%E8%BE%91%E5%AD%98%E5%9C%A8%E7%BC%BA%E9%99%B7\" target=\"_blank\"><img border=\"0\" src=\"http://res3.feedsportal.com/social/googleplus.png\" /></a>&nbsp;<a href=\"http://share.feedsportal.com/share/email/?u=http%3A%2F%2Fwww.cnbeta.com%2Farticles%2F244891.htm&amp;t=%E3%80%8A%E6%97%B6%E4%BB%A3%E3%80%8B%E6%9D%82%E5%BF%97%EF%BC%9A%E5%BE%AE%E8%BD%AFWindows+8%E8%AE%BE%E8%AE%A1%E9%80%BB%E8%BE%91%E5%AD%98%E5%9C%A8%E7%BC%BA%E9%99%B7\" target=\"_blank\"><img border=\"0\" src=\"http://res3.feedsportal.com/social/email.png\" /></a></td><td valign=\"middle\"></td></tr></table></div><br /><br /><a href=\"http://da.feedsportal.com/r/165666653719/u/0/f/624776/c/34306/s/2eb9b1c9/a2.htm\"><img border=\"0\" src=\"http://da.feedsportal.com/r/165666653719/u/0/f/624776/c/34306/s/2eb9b1c9/a2.img\" /></a><img border=\"0\" height=\"1\" src=\"http://pi.feedsportal.com/r/165666653719/u/0/f/624776/c/34306/s/2eb9b1c9/a2t.img\" width=\"1\" />", 
  "title": "《时代》杂志：微软Windows 8设计逻辑存在缺陷"
 }, 
 {
  "date": "Tue, 16 Jul 2013 10:50:37 GMT", 
  "link": "http://www.cnbeta.com/articles/244890.htm", 
  "description": "<p><strong>钢铁侠的强悍，超人的威猛，今年超级英雄们为我们带来了视觉盛宴，也引来我们无限遐想。超级英雄们的超高战斗力，我们普通人可以利用高科技装备，在现实中变身为超级英雄吗？</strong></p><img border=\"0\" height=\"1\" src=\"http://cnbeta.feedsportal.com/c/34306/f/624776/s/2eb9b1c8/mf.gif\" width=\"1\" /><div class=\"mf-viral\"><table border=\"0\"><tr><td valign=\"middle\"><a href=\"http://share.feedsportal.com/share/twitter/?u=http%3A%2F%2Fwww.cnbeta.com%2Farticles%2F244890.htm&amp;t=%E7%A9%BF%E4%B8%8A%E9%AB%98%E7%A7%91%E6%8A%80%E5%8F%98%E8%BA%AB%E8%B6%85%E7%BA%A7%E8%8B%B1%E9%9B%84\" target=\"_blank\"><img border=\"0\" src=\"http://res3.feedsportal.com/social/twitter.png\" /></a>&nbsp;<a href=\"http://share.feedsportal.com/share/facebook/?u=http%3A%2F%2Fwww.cnbeta.com%2Farticles%2F244890.htm&amp;t=%E7%A9%BF%E4%B8%8A%E9%AB%98%E7%A7%91%E6%8A%80%E5%8F%98%E8%BA%AB%E8%B6%85%E7%BA%A7%E8%8B%B1%E9%9B%84\" target=\"_blank\"><img border=\"0\" src=\"http://res3.feedsportal.com/social/facebook.png\" /></a>&nbsp;<a href=\"http://share.feedsportal.com/share/linkedin/?u=http%3A%2F%2Fwww.cnbeta.com%2Farticles%2F244890.htm&amp;t=%E7%A9%BF%E4%B8%8A%E9%AB%98%E7%A7%91%E6%8A%80%E5%8F%98%E8%BA%AB%E8%B6%85%E7%BA%A7%E8%8B%B1%E9%9B%84\" target=\"_blank\"><img border=\"0\" src=\"http://res3.feedsportal.com/social/linkedin.png\" /></a>&nbsp;<a href=\"http://share.feedsportal.com/share/gplus/?u=http%3A%2F%2Fwww.cnbeta.com%2Farticles%2F244890.htm&amp;t=%E7%A9%BF%E4%B8%8A%E9%AB%98%E7%A7%91%E6%8A%80%E5%8F%98%E8%BA%AB%E8%B6%85%E7%BA%A7%E8%8B%B1%E9%9B%84\" target=\"_blank\"><img border=\"0\" src=\"http://res3.feedsportal.com/social/googleplus.png\" /></a>&nbsp;<a href=\"http://share.feedsportal.com/share/email/?u=http%3A%2F%2Fwww.cnbeta.com%2Farticles%2F244890.htm&amp;t=%E7%A9%BF%E4%B8%8A%E9%AB%98%E7%A7%91%E6%8A%80%E5%8F%98%E8%BA%AB%E8%B6%85%E7%BA%A7%E8%8B%B1%E9%9B%84\" target=\"_blank\"><img border=\"0\" src=\"http://res3.feedsportal.com/social/email.png\" /></a></td><td valign=\"middle\"></td></tr></table></div><br /><br /><a href=\"http://da.feedsportal.com/r/165666653717/u/0/f/624776/c/34306/s/2eb9b1c8/a2.htm\"><img border=\"0\" src=\"http://da.feedsportal.com/r/165666653717/u/0/f/624776/c/34306/s/2eb9b1c8/a2.img\" /></a><img border=\"0\" height=\"1\" src=\"http://pi.feedsportal.com/r/165666653717/u/0/f/624776/c/34306/s/2eb9b1c8/a2t.img\" width=\"1\" />", 
  "title": "穿上高科技变身超级英雄"
 }, 
 {
  "date": "Tue, 16 Jul 2013 10:48:48 GMT", 
  "link": "http://www.cnbeta.com/articles/244889.htm", 
  "description": "<p>淘宝网负责人语嫣今日通过淘宝网官方微博表示，今明两年淘宝网的整体运营思路是做卖家支撑。语嫣在题为““玩儿法变了”的长微博中表示，淘宝下半年会推“淘字号”，卖家可为淘宝店铺重命名，并且要求不能重名，同时将打通搜索名称进入店铺的通道。<strong>以下为原文：</strong></p><img border=\"0\" height=\"1\" src=\"http://cnbeta.feedsportal.com/c/34306/f/624776/s/2eb9b1c5/mf.gif\" width=\"1\" /><div class=\"mf-viral\"><table border=\"0\"><tr><td valign=\"middle\"><a href=\"http://share.feedsportal.com/share/twitter/?u=http%3A%2F%2Fwww.cnbeta.com%2Farticles%2F244889.htm&amp;t=%E6%B7%98%E5%AE%9D%E8%B4%9F%E8%B4%A3%E4%BA%BA%E8%AF%A6%E8%A7%A3%E8%BF%90%E8%90%A5%E7%AD%96%E7%95%A5%EF%BC%9A%E5%B0%86%E6%8E%A8%E4%B8%8D%E9%87%8D%E5%90%8D%E5%BA%97%E9%93%BA%E5%AD%97%E5%8F%B7\" target=\"_blank\"><img border=\"0\" src=\"http://res3.feedsportal.com/social/twitter.png\" /></a>&nbsp;<a href=\"http://share.feedsportal.com/share/facebook/?u=http%3A%2F%2Fwww.cnbeta.com%2Farticles%2F244889.htm&amp;t=%E6%B7%98%E5%AE%9D%E8%B4%9F%E8%B4%A3%E4%BA%BA%E8%AF%A6%E8%A7%A3%E8%BF%90%E8%90%A5%E7%AD%96%E7%95%A5%EF%BC%9A%E5%B0%86%E6%8E%A8%E4%B8%8D%E9%87%8D%E5%90%8D%E5%BA%97%E9%93%BA%E5%AD%97%E5%8F%B7\" target=\"_blank\"><img border=\"0\" src=\"http://res3.feedsportal.com/social/facebook.png\" /></a>&nbsp;<a href=\"http://share.feedsportal.com/share/linkedin/?u=http%3A%2F%2Fwww.cnbeta.com%2Farticles%2F244889.htm&amp;t=%E6%B7%98%E5%AE%9D%E8%B4%9F%E8%B4%A3%E4%BA%BA%E8%AF%A6%E8%A7%A3%E8%BF%90%E8%90%A5%E7%AD%96%E7%95%A5%EF%BC%9A%E5%B0%86%E6%8E%A8%E4%B8%8D%E9%87%8D%E5%90%8D%E5%BA%97%E9%93%BA%E5%AD%97%E5%8F%B7\" target=\"_blank\"><img border=\"0\" src=\"http://res3.feedsportal.com/social/linkedin.png\" /></a>&nbsp;<a href=\"http://share.feedsportal.com/share/gplus/?u=http%3A%2F%2Fwww.cnbeta.com%2Farticles%2F244889.htm&amp;t=%E6%B7%98%E5%AE%9D%E8%B4%9F%E8%B4%A3%E4%BA%BA%E8%AF%A6%E8%A7%A3%E8%BF%90%E8%90%A5%E7%AD%96%E7%95%A5%EF%BC%9A%E5%B0%86%E6%8E%A8%E4%B8%8D%E9%87%8D%E5%90%8D%E5%BA%97%E9%93%BA%E5%AD%97%E5%8F%B7\" target=\"_blank\"><img border=\"0\" src=\"http://res3.feedsportal.com/social/googleplus.png\" /></a>&nbsp;<a href=\"http://share.feedsportal.com/share/email/?u=http%3A%2F%2Fwww.cnbeta.com%2Farticles%2F244889.htm&amp;t=%E6%B7%98%E5%AE%9D%E8%B4%9F%E8%B4%A3%E4%BA%BA%E8%AF%A6%E8%A7%A3%E8%BF%90%E8%90%A5%E7%AD%96%E7%95%A5%EF%BC%9A%E5%B0%86%E6%8E%A8%E4%B8%8D%E9%87%8D%E5%90%8D%E5%BA%97%E9%93%BA%E5%AD%97%E5%8F%B7\" target=\"_blank\"><img border=\"0\" src=\"http://res3.feedsportal.com/social/email.png\" /></a></td><td valign=\"middle\"></td></tr></table></div><br /><br /><a href=\"http://da.feedsportal.com/r/165666653716/u/0/f/624776/c/34306/s/2eb9b1c5/a2.htm\"><img border=\"0\" src=\"http://da.feedsportal.com/r/165666653716/u/0/f/624776/c/34306/s/2eb9b1c5/a2.img\" /></a><img border=\"0\" height=\"1\" src=\"http://pi.feedsportal.com/r/165666653716/u/0/f/624776/c/34306/s/2eb9b1c5/a2t.img\" width=\"1\" />", 
  "title": "淘宝负责人详解运营策略：将推不重名店铺字号"
 }
]