[
 {
  "date": "Tue, 18 Jun 2013 05:22:00 GMT", 
  "link": "http://www.cnbeta.com/articles/241541.htm", 
  "description": "虽然苹果公司与美国司法部之间的电子书定价诉讼案没有什么有意思的地方，不过据AllThingsD的报道，出庭作证的苹果SVP Eddy Cue却因此介绍了一些关于苹果已故创始人乔布斯和苹果iBooks之间的故事。<b>根据Eddy Cue的描述，iBooks应用中的卷动翻页模式――当点击iBooks电子书页面就会出现的类似真实翻书感觉的样子，这个想法实际上是由乔布斯提出来的。</b><img border=\"0\" height=\"1\" src=\"http://cnbeta.feedsportal.com/c/34306/f/624776/s/2d6d598b/mf.gif\" width=\"1\" /><div class=\"mf-viral\"><table border=\"0\"><tr><td valign=\"middle\"><a href=\"http://share.feedsportal.com/share/twitter/?u=http%3A%2F%2Fwww.cnbeta.com%2Farticles%2F241541.htm&amp;t=%E4%B9%94%E5%B8%83%E6%96%AF%E6%83%B3%E5%87%BAiBooks%E5%8D%B7%E5%8A%A8%E7%BF%BB%E9%A1%B5%E6%A8%A1%E5%BC%8F%EF%BC%8C%E8%BF%98%E6%9C%89%E7%BB%B4%E5%B0%BC%E7%86%8A%E3%80%81%E8%82%AF%E5%B0%BC%E8%BF%AA\" target=\"_blank\"><img border=\"0\" src=\"http://res3.feedsportal.com/social/twitter.png\" /></a>&nbsp;<a href=\"http://share.feedsportal.com/share/facebook/?u=http%3A%2F%2Fwww.cnbeta.com%2Farticles%2F241541.htm&amp;t=%E4%B9%94%E5%B8%83%E6%96%AF%E6%83%B3%E5%87%BAiBooks%E5%8D%B7%E5%8A%A8%E7%BF%BB%E9%A1%B5%E6%A8%A1%E5%BC%8F%EF%BC%8C%E8%BF%98%E6%9C%89%E7%BB%B4%E5%B0%BC%E7%86%8A%E3%80%81%E8%82%AF%E5%B0%BC%E8%BF%AA\" target=\"_blank\"><img border=\"0\" src=\"http://res3.feedsportal.com/social/facebook.png\" /></a>&nbsp;<a href=\"http://share.feedsportal.com/share/linkedin/?u=http%3A%2F%2Fwww.cnbeta.com%2Farticles%2F241541.htm&amp;t=%E4%B9%94%E5%B8%83%E6%96%AF%E6%83%B3%E5%87%BAiBooks%E5%8D%B7%E5%8A%A8%E7%BF%BB%E9%A1%B5%E6%A8%A1%E5%BC%8F%EF%BC%8C%E8%BF%98%E6%9C%89%E7%BB%B4%E5%B0%BC%E7%86%8A%E3%80%81%E8%82%AF%E5%B0%BC%E8%BF%AA\" target=\"_blank\"><img border=\"0\" src=\"http://res3.feedsportal.com/social/linkedin.png\" /></a>&nbsp;<a href=\"http://share.feedsportal.com/share/gplus/?u=http%3A%2F%2Fwww.cnbeta.com%2Farticles%2F241541.htm&amp;t=%E4%B9%94%E5%B8%83%E6%96%AF%E6%83%B3%E5%87%BAiBooks%E5%8D%B7%E5%8A%A8%E7%BF%BB%E9%A1%B5%E6%A8%A1%E5%BC%8F%EF%BC%8C%E8%BF%98%E6%9C%89%E7%BB%B4%E5%B0%BC%E7%86%8A%E3%80%81%E8%82%AF%E5%B0%BC%E8%BF%AA\" target=\"_blank\"><img border=\"0\" src=\"http://res3.feedsportal.com/social/googleplus.png\" /></a>&nbsp;<a href=\"http://share.feedsportal.com/share/email/?u=http%3A%2F%2Fwww.cnbeta.com%2Farticles%2F241541.htm&amp;t=%E4%B9%94%E5%B8%83%E6%96%AF%E6%83%B3%E5%87%BAiBooks%E5%8D%B7%E5%8A%A8%E7%BF%BB%E9%A1%B5%E6%A8%A1%E5%BC%8F%EF%BC%8C%E8%BF%98%E6%9C%89%E7%BB%B4%E5%B0%BC%E7%86%8A%E3%80%81%E8%82%AF%E5%B0%BC%E8%BF%AA\" target=\"_blank\"><img border=\"0\" src=\"http://res3.feedsportal.com/social/email.png\" /></a></td><td valign=\"middle\"></td></tr></table></div><br /><br /><a href=\"http://da.feedsportal.com/r/165665644609/u/0/f/624776/c/34306/s/2d6d598b/a2.htm\"><img border=\"0\" src=\"http://da.feedsportal.com/r/165665644609/u/0/f/624776/c/34306/s/2d6d598b/a2.img\" /></a><img border=\"0\" height=\"1\" src=\"http://pi.feedsportal.com/r/165665644609/u/0/f/624776/c/34306/s/2d6d598b/a2t.img\" width=\"1\" />", 
  "title": "乔布斯想出iBooks卷动翻页模式，还有维尼熊、肯尼迪"
 }, 
 {
  "date": "Tue, 18 Jun 2013 05:20:12 GMT", 
  "link": "http://www.cnbeta.com/articles/241540.htm", 
  "description": "<b>继特供机之后，奇虎360正式涉足硬件领域，推出便捷路由器产品“360随身Wifi”――只要将其插到任何一台可以上网的电脑上，不用做任何设置，手机、Pad等智能设备就可上网。</b>目前，这款产品今日已登陆360官网开售，售价19.9元。<img border=\"0\" height=\"1\" src=\"http://cnbeta.feedsportal.com/c/34306/f/624776/s/2d6d598a/mf.gif\" width=\"1\" /><div class=\"mf-viral\"><table border=\"0\"><tr><td valign=\"middle\"><a href=\"http://share.feedsportal.com/share/twitter/?u=http%3A%2F%2Fwww.cnbeta.com%2Farticles%2F241540.htm&amp;t=360%E5%8F%91%E5%B8%83%E4%BE%BF%E6%8D%B7%E8%B7%AF%E7%94%B1%E5%99%A8%E2%80%9C360%E9%9A%8F%E8%BA%ABWi-fi%E2%80%9D+%E5%94%AE%E4%BB%B719.9%E5%85%83\" target=\"_blank\"><img border=\"0\" src=\"http://res3.feedsportal.com/social/twitter.png\" /></a>&nbsp;<a href=\"http://share.feedsportal.com/share/facebook/?u=http%3A%2F%2Fwww.cnbeta.com%2Farticles%2F241540.htm&amp;t=360%E5%8F%91%E5%B8%83%E4%BE%BF%E6%8D%B7%E8%B7%AF%E7%94%B1%E5%99%A8%E2%80%9C360%E9%9A%8F%E8%BA%ABWi-fi%E2%80%9D+%E5%94%AE%E4%BB%B719.9%E5%85%83\" target=\"_blank\"><img border=\"0\" src=\"http://res3.feedsportal.com/social/facebook.png\" /></a>&nbsp;<a href=\"http://share.feedsportal.com/share/linkedin/?u=http%3A%2F%2Fwww.cnbeta.com%2Farticles%2F241540.htm&amp;t=360%E5%8F%91%E5%B8%83%E4%BE%BF%E6%8D%B7%E8%B7%AF%E7%94%B1%E5%99%A8%E2%80%9C360%E9%9A%8F%E8%BA%ABWi-fi%E2%80%9D+%E5%94%AE%E4%BB%B719.9%E5%85%83\" target=\"_blank\"><img border=\"0\" src=\"http://res3.feedsportal.com/social/linkedin.png\" /></a>&nbsp;<a href=\"http://share.feedsportal.com/share/gplus/?u=http%3A%2F%2Fwww.cnbeta.com%2Farticles%2F241540.htm&amp;t=360%E5%8F%91%E5%B8%83%E4%BE%BF%E6%8D%B7%E8%B7%AF%E7%94%B1%E5%99%A8%E2%80%9C360%E9%9A%8F%E8%BA%ABWi-fi%E2%80%9D+%E5%94%AE%E4%BB%B719.9%E5%85%83\" target=\"_blank\"><img border=\"0\" src=\"http://res3.feedsportal.com/social/googleplus.png\" /></a>&nbsp;<a href=\"http://share.feedsportal.com/share/email/?u=http%3A%2F%2Fwww.cnbeta.com%2Farticles%2F241540.htm&amp;t=360%E5%8F%91%E5%B8%83%E4%BE%BF%E6%8D%B7%E8%B7%AF%E7%94%B1%E5%99%A8%E2%80%9C360%E9%9A%8F%E8%BA%ABWi-fi%E2%80%9D+%E5%94%AE%E4%BB%B719.9%E5%85%83\" target=\"_blank\"><img border=\"0\" src=\"http://res3.feedsportal.com/social/email.png\" /></a></td><td valign=\"middle\"></td></tr></table></div><br /><br /><a href=\"http://da.feedsportal.com/r/165665644607/u/0/f/624776/c/34306/s/2d6d598a/a2.htm\"><img border=\"0\" src=\"http://da.feedsportal.com/r/165665644607/u/0/f/624776/c/34306/s/2d6d598a/a2.img\" /></a><img border=\"0\" height=\"1\" src=\"http://pi.feedsportal.com/r/165665644607/u/0/f/624776/c/34306/s/2d6d598a/a2t.img\" width=\"1\" />", 
  "title": "360发布便捷路由器“360随身Wi-fi” 售价19.9元"
 }
]