[
 {
  "date": "Mon, 07 Dec 2015 06:57:17 GMT", 
  "link": "http://www.cnbeta.com/articles/454797.htm", 
  "description": "虽然事故已经过去好几年，但日核泄漏污染增加依然引起人们关注。作为切尔克贝利核泄漏以来最严重的核灾难，即便日本政府尝试隐瞒，人们依然能感受到福岛的绝望与无奈。<strong>美国科学家认为日本福岛核电站事故发生四年后，仍有放射性物质泄漏。日核泄漏污染增加，福岛核电站周围16万居民被迫撤离。如今这里依然危险，但大自然将废墟改造成一片荒野。</strong>", 
  "title": "日本核泄漏污染增加 福岛成全球最危险鬼城"
 }, 
 {
  "date": "Mon, 07 Dec 2015 06:55:31 GMT", 
  "link": "http://www.cnbeta.com/articles/454795.htm", 
  "description": "<strong>一名70后力哥，心血来潮在某聊天工具上注册一个账号，起名“包养你”。结果还真有人与他接洽“包养”，两名90后美女，先后与他开房，手机、现金、手表、银行卡等被盗走。</strong>4日，江北警方花园村派出所对力哥黄某（化名）执行逮捕。", 
  "title": "力哥起网名“包养你” 两90后美女上当"
 }
]